degooged_tube/__init__.py
degooged_tube/cli.py
degooged_tube/commands.py
degooged_tube/config.py
degooged_tube/helpers.py
degooged_tube/mpvWrapper.py
degooged_tube/prompts.py
degooged_tube/subbox.py
degooged_tube/subboxChannel.py
degooged_tube/ytDlpWrapper.py
degooged_tube/ytApiHacking/__init__.py
degooged_tube/ytApiHacking/controlPanel.py
degooged_tube/ytApiHacking/customExceptions.py
degooged_tube/ytApiHacking/helpers.py
degooged_tube/ytApiHacking/ytApiList.py
degooged_tube/ytApiHacking/ytContIter.py
degooged_tube/ytApiHacking/ytInitalPage.py
degooged_tube/ytApiHacking/jsonScraping/__init__.py
degooged_tube/ytApiHacking/jsonScraping/basicScraping.py
degooged_tube/ytApiHacking/jsonScraping/scrapeJsonTree.py
degooged_tube-1.0.2.data/scripts/degooged-tube
degooged_tube-1.0.2.dist-info/LICENCE
degooged_tube-1.0.2.dist-info/METADATA
degooged_tube-1.0.2.dist-info/WHEEL
degooged_tube-1.0.2.dist-info/entry_points.txt
degooged_tube-1.0.2.dist-info/top_level.txt
degooged_tube-1.0.2.dist-info/RECORD
