Metadata-Version: 2.1
Name: degooged-tube
Version: 1.0.2
Summary: An adless, accountless, trackerless youtube interface with a sub box
Home-page: https://github.com/PrinceOfPuppers/degooged-tube
Author: Joshua McPherson
Author-email: joshuamcpherson5@gmail.com
Classifier: Programming Language :: Python :: 3
Classifier: License :: OSI Approved :: MIT License
Classifier: Operating System :: OS Independent
Classifier: Environment :: Console
Classifier: Intended Audience :: End Users/Desktop
Requires-Python: >=3.6
License-File: LICENCE
Requires-Dist: requests
Requires-Dist: yt-dlp
Requires-Dist: python-mpv
